{
         "ARRIVALS":[
            {
               
                "img":"https://images.bewakoof.com/t320/men-classic-mickey-f-b-printed-t-shirt-563360-1672312100-1.jpg",
                "brand":"Bewakoof",
                "title":"Men's Red & White Classi...",
                 "price": 899,
                 "strike":1799,
                 "off":"50%"

            },
            {
                
                 "img":"https://images.bewakoof.com/t320/men-s-white-mood-of-the-day-panda-graphic-printed-t-shirt-519193-1667511472-1.jpg",
                 "brand":"Bewakoof",
                 "title":"Men's White Mood of ...",
                  "price": 494,
                  "strike":1299,
                  "off":"61%"
 
             },
             {
                
                 "img":"https://images.bewakoof.com/t320/men-mickey-face-strip-printed-t-shirt-563355-1672134081-1.jpg",
                 "brand":"Bewakoof",
                 "title":"Men's Black Mood of ...",
                  "price": 899,
                  "strike":1799,
                  "off":"50%"
 
             },
             {
                
                 "img":"https://images.bewakoof.com/t320/men-ceylon-yellow-find-your-minion-printed-t-shirt-540892-1666703797-1.jpg",
                 "brand":"Bewakoof",
                 "title":"Men's Yellow Mood of ...",
                  "price": 499,
                  "strike":799,
                  "off":"43%"
 
             },
             {
                
                 "img":"https://images.bewakoof.com/t320/men-s-green-travelling-cat-graphic-printed-oversized-t-shirt-552846-1669294763-1.jpg",
                 "brand":"Bewakoof",
                 "title":"Men's Green Travelling ...",
                  "price": 857,
                  "strike":1799,
                  "off":"50%"
 
             },
             {
                
                 "img":"https://images.bewakoof.com/t320/men-mickey-crew-stripe-printed-t-shirt-563365-1672135232-1.jpg",
                 "brand":"Bewakoof",
                 "title":"Men's Black Mickey of ...",
                  "price": 657,
                  "strike":1399,
                  "off":"53%"
 
             },
             {
                
                 "img":"https://images.bewakoof.com/t320/men-spiral-mickey-printed-t-shirt-563364-1672134161-1.jpg",
                 "brand":"Bewakoof",
                 "title":"Men's Black Mickey of ...",
                  "price": 857,
                  "strike":1799,
                  "off":"53%"
 
             },
             {
                
                 "img":"https://images.bewakoof.com/t320/men-classic-mickey-f-b-printed-t-shirt-563341-1672312142-1.jpg",
                 "brand":"Bewakoof",
                 "title":"Men's Acid washed...",
                  "price": 799,
                  "strike":1799,
                  "off":"50%"
 
             },
             {
                
                 "img":"",
                 "brand":"Bewakoof",
                 "title":"",
                  "price": 857,
                  "strike":1799,
                  "off":"50%"
 
             },
             {
                
                 "img":"https://images.bewakoof.com/t320/men-purple-rose-troublemakers-trio-printed-t-shirt-546632-1667828378-1.jpg",
                 "brand":"Bewakoof",
                 "title":"Men's Purple Ross...",
                  "price": 699,
                  "strike":1299,
                  "off":"46%"
 
             }
         ]
        
     }
         


     


